openssl_sign_certs/__init__.py
openssl_sign_certs/__main__.py
openssl_sign_certs/program/__init__.py
openssl_sign_certs/program/parser.py
openssl_sign_certs/program/sign_certs.py
openssl_sign_certs/program/statics.py
openssl_sign_certs-1.0.1.post1.dist-info/DESCRIPTION.rst
openssl_sign_certs-1.0.1.post1.dist-info/METADATA
openssl_sign_certs-1.0.1.post1.dist-info/RECORD
openssl_sign_certs-1.0.1.post1.dist-info/WHEEL
openssl_sign_certs-1.0.1.post1.dist-info/entry_points.txt
openssl_sign_certs-1.0.1.post1.dist-info/metadata.json
openssl_sign_certs-1.0.1.post1.dist-info/top_level.txt
openssl_sign_certs-1.0.1.post1.dist-info/zip-safe
